{
  "oracle": {
    "top_matching_factors": [
      "fear_greed",
      "btc_momentum_30d",
      "stablecoin_growth"
    ],
    "diverging_factors": [
      "dxy_weakness",
      "gold_strength",
      "vix"
    ],
    "oracle_verdict": "APPROACHING",
    "phase": "Disbelief",
    "regime_direction": "RISK_OFF",
    "classifier_signal": "CAUTION",
    "confidence": 0.85,
    "raw_response": "{\n  \"top_matching_factors\": [\"fear_greed\", \"btc_momentum_30d\", \"stablecoin_growth\"],\n  \"diverging_factors\": [\"dxy_weakness\", \"gold_strength\", \"vix\"],\n  \"oracle_verdict\": \"APPROACHING\",\n  \"phase\": \"Disbelief\",\n  \"regime_direction\": \"RISK_OFF\",\n  \"classifier_signal\": \"CAUTION\",\n  \"confidence\": 0.85\n}",
    "brain": "analyst"
  },
  "classifier": {
    "top_matching_factors": [
      "fear_greed",
      "btc_momentum_30d",
      "stablecoin_growth"
    ],
    "diverging_factors": [
      "dxy_weakness",
      "gold_strength",
      "vix"
    ],
    "oracle_verdict": "APPROACHING",
    "phase": "Disbelief",
    "regime_direction": "RISK_OFF",
    "classifier_signal": "CAUTION",
    "confidence": 0.85,
    "raw_response": "{\n  \"top_matching_factors\": [\"fear_greed\", \"btc_momentum_30d\", \"stablecoin_growth\"],\n  \"diverging_factors\": [\"dxy_weakness\", \"gold_strength\", \"vix\"],\n  \"oracle_verdict\": \"APPROACHING\",\n  \"phase\": \"Disbelief\",\n  \"regime_direction\": \"RISK_OFF\",\n  \"classifier_signal\": \"CAUTION\",\n  \"confidence\": 0.85\n}",
    "brain": "analyst"
  },
  "analyst": {
    "top_matching_factors": [
      "fear_greed",
      "btc_momentum_30d",
      "stablecoin_growth"
    ],
    "diverging_factors": [
      "dxy_weakness",
      "gold_strength",
      "vix"
    ],
    "oracle_verdict": "APPROACHING",
    "phase": "Disbelief",
    "regime_direction": "RISK_OFF",
    "classifier_signal": "CAUTION",
    "confidence": 0.85,
    "raw_response": "{\n  \"top_matching_factors\": [\"fear_greed\", \"btc_momentum_30d\", \"stablecoin_growth\"],\n  \"diverging_factors\": [\"dxy_weakness\", \"gold_strength\", \"vix\"],\n  \"oracle_verdict\": \"APPROACHING\",\n  \"phase\": \"Disbelief\",\n  \"regime_direction\": \"RISK_OFF\",\n  \"classifier_signal\": \"CAUTION\",\n  \"confidence\": 0.85\n}",
    "brain": "analyst"
  },
  "narrative": {
    "narrative": "Prolonged market uncertainty fueled by low Fear & Greed (12) and BTC's sluggish momentum (-0.13% in 24h) mirrors August 2024's disbelief phase, suggesting a potential retest of recent lows.",
    "headline": "Market Anxiety Persists as BTC Momentum Falters",
    "confidence": 0.85,
    "raw_response": "{\"narrative\": \"Prolonged market uncertainty fueled by low Fear & Greed (12) and BTC's sluggish momentum (-0.13% in 24h) mirrors August 2024's disbelief phase, suggesting a potential retest of recent lows.\", \"headline\": \"Market Anxiety Persists as BTC Momentum Falters\", \"confidence\": 0.85}",
    "brain": "narrative_writer"
  },
  "consensus": {
    "final_signal": "CAUTION",
    "final_phase": "Disbelief",
    "alert_tier": "CRITICAL",
    "consensus_confidence": 0.85,
    "key_reasoning": "Both experts agree on the Disbelief phase, with Pattern Analyst signaling caution and Narrative Writer emphasizing market anxiety and potential retest of recent lows.",
    "disagreements_noted": [],
    "raw_response": "```json\n{\n  \"final_signal\": \"CAUTION\",\n  \"final_phase\": \"Disbelief\",\n  \"alert_tier\": \"CRITICAL\",\n  \"consensus_confidence\": 0.85,\n  \"key_reasoning\": \"Both experts agree on the Disbelief phase, with Pattern Analyst signaling caution and Narrative Writer emphasizing market anxiety and potential retest of recent lows.\",\n  \"disagreements_noted\": []\n}\n```",
    "brain": "consensus_judge",
    "brains_avg_confidence": 0.85,
    "brain_reads": {
      "analyst": {
        "signal": "CAUTION",
        "phase": "Disbelief",
        "verdict": "APPROACHING",
        "confidence": 0.85
      },
      "narrative": {
        "headline": "Market Anxiety Persists as BTC Momentum Falters",
        "confidence": 0.85
      },
      "judge": {
        "signal": "CAUTION",
        "confidence": null
      }
    },
    "advisory": true
  },
  "timestamp": "2026-06-12T18:13:58.836845-04:00",
  "architecture": "3-brain-sequential-v2.4"
}