{
  "_updated": "2026-06-29T08:01:22.440797-04:00",
  "_version": "v2.7",
  "_doctrine": "Empire's daily synthesis packet. Phase + trend + cliff_proximity + analogues + recommendation. Read by perps/kalshi/sniper/Jordan.",
  "sweep_interval_min": 60,
  "current_score": 38,
  "current_phase": "Panic",
  "phase_source": "jordan",
  "phase_suggestion": "Panic",
  "trend": "flat",
  "phase_leg": "flat",
  "cliff_proximity": "low",
  "forecast": {
    "next_top_score": 73.0,
    "next_top_weeks_out": 77,
    "next_bottom_score": 17.4,
    "next_bottom_weeks_out": 0,
    "score_7d_target": 17.4,
    "da_score_7d_target": 82.6,
    "amplitude_blend": 0.35,
    "method": "weighted_mean_plus_primary_blend"
  },
  "horse_race": {
    "state": "unknown",
    "jordan_winning_line": "j6",
    "jordan_horse_race_read": "j6 line leading due to empire intel adding alpha in this panic phase flat with aug 2024 bottom analogue dominant",
    "forecast_residual": 18.8,
    "da_residual": 42.8,
    "j6_residual": 18.0,
    "regime_break": false
  },
  "historical_analogues": [
    {
      "name": "bottom_2022_may_luna",
      "similarity": 0.808,
      "weight": 0.3367,
      "fingerprint_date": "2022-05-12",
      "fingerprint_type": "liquidation_bottom"
    },
    {
      "name": "bottom_2018_dec",
      "similarity": 0.7964,
      "weight": 0.3319,
      "fingerprint_date": "2018-12-15",
      "fingerprint_type": "cycle_bottom"
    },
    {
      "name": "bottom_2020_mar",
      "similarity": 0.7952,
      "weight": 0.3314,
      "fingerprint_date": "2020-03-12",
      "fingerprint_type": "liquidity_bottom"
    }
  ],
  "active_signal_inputs": {
    "envelope_count": 412,
    "by_source": {
      "crucix": 210,
      "flow_cycle": 8,
      "jordan_scraper": 17,
      "news_catalyst": 146,
      "polymarket": 31
    },
    "by_severity": {
      "critical": 254,
      "medium": 75,
      "high": 67,
      "low": 16
    },
    "by_direction": {
      "bearish": 163,
      "ambiguous": 190,
      "neutral": 29,
      "bullish": 30
    },
    "weighted_bullish_score": 3.216,
    "weighted_bearish_score": 63.161,
    "net_signal": "bearish",
    "confluence_clusters": [
      {
        "synthetic_envelope_id": "flow_confluence_1782734482_dd0720",
        "window": "15min",
        "direction": "bearish",
        "source_count": 2,
        "sources": [
          "crucix",
          "news_catalyst"
        ],
        "strength": 4.497,
        "severity": "critical",
        "summary": "2-source bearish confluence (15min window): [crucix:energy] strength=10/10 keywords=[oil, gas, crude, wti, brent] \u2014 oil spik",
        "member_envelope_ids": [
          "crucix_energy_1782734482_9e940f",
          "crucix_geo_political_1782734482_142dc7",
          "crucix_sustained_energy_1782734482_573b3b",
          "crucix_sustained_geo_political_1782734482_b31e65",
          "news_catalyst_1782733797_b8592f"
        ]
      },
      {
        "synthetic_envelope_id": "flow_confluence_1782734482_7d1f4a",
        "window": "1h",
        "direction": "bearish",
        "source_count": 2,
        "sources": [
          "crucix",
          "news_catalyst"
        ],
        "strength": 4.497,
        "severity": "critical",
        "summary": "2-source bearish confluence (1h window): [crucix:energy] strength=10/10 keywords=[oil, gas, crude, wti, brent] \u2014 oil spik",
        "member_envelope_ids": [
          "crucix_energy_1782734482_9e940f",
          "crucix_geo_political_1782734482_142dc7",
          "crucix_sustained_energy_1782734482_573b3b",
          "crucix_sustained_geo_political_1782734482_b31e65",
          "news_catalyst_1782733797_b8592f"
        ]
      },
      {
        "synthetic_envelope_id": "flow_confluence_1782734482_15c667",
        "window": "6h",
        "direction": "bearish",
        "source_count": 3,
        "sources": [
          "crucix",
          "flow_cycle",
          "news_catalyst"
        ],
        "strength": 37.093,
        "severity": "critical",
        "summary": "3-source bearish confluence (6h window): [crucix:energy] strength=10/10 keywords=[oil, gas, crude, wti, brent] \u2014 oil spik",
        "member_envelope_ids": [
          "crucix_energy_1782713297_0cbcd5",
          "crucix_energy_1782717470_d3500d",
          "crucix_energy_1782721745_edfb59",
          "crucix_energy_1782726030_5ff930",
          "crucix_energy_1782730240_5188ac",
          "crucix_energy_1782734482_9e940f",
          "crucix_geo_political_1782713297_d9795c",
          "crucix_geo_political_1782717470_ad4287",
          "crucix_geo_political_1782721745_2ffc9d",
          "crucix_geo_political_1782726030_b34904",
          "crucix_geo_political_1782730240_a93a39",
          "crucix_geo_political_1782734482_142dc7",
          "crucix_sustained_energy_1782713297_2a8a0b",
          "crucix_sustained_energy_1782717470_624ff3",
          "crucix_sustained_energy_1782721745_550b64",
          "crucix_sustained_energy_1782726030_71b306",
          "crucix_sustained_energy_1782730240_0206d9",
          "crucix_sustained_energy_1782734482_573b3b",
          "crucix_sustained_geo_political_1782713297_9a53e3",
          "crucix_sustained_geo_political_1782717470_16a761",
          "crucix_sustained_geo_political_1782721745_ed4a40",
          "crucix_sustained_geo_political_1782726030_7c805b",
          "crucix_sustained_geo_political_1782730240_803579",
          "crucix_sustained_geo_political_1782734482_b31e65",
          "flow_confluence_1782721746_010e41",
          "flow_confluence_1782721746_9d8ea2",
          "flow_confluence_1782726030_2ab56d",
          "flow_confluence_1782726030_941181",
          "flow_confluence_1782726030_e52e27",
          "flow_confluence_1782730240_116924",
          "flow_confluence_1782730240_1efa6e",
          "flow_confluence_1782730240_78bef0",
          "news_catalyst_1782716860_7d3921",
          "news_catalyst_1782719577_4fbec0",
          "news_catalyst_1782725335_7b4750",
          "news_catalyst_1782725345_109463",
          "news_catalyst_1782725363_ea4c43",
          "news_catalyst_1782725381_f3d4d9",
          "news_catalyst_1782725384_51f765",
          "news_catalyst_1782726858_0b6cab",
          "news_catalyst_1782729562_4b3db0",
          "news_catalyst_1782729608_eadd62",
          "news_catalyst_1782733797_b8592f",
          "news_catalyst_sustained_1782719625_f4afda",
          "news_catalyst_sustained_1782725384_d1f51f",
          "news_catalyst_sustained_1782729608_5bab74"
        ]
      }
    ],
    "regime_break_envelopes": [],
    "top_envelopes_by_weight": [
      {
        "id": "crucix_sustained_energy_1782734482_573b3b",
        "headline": "[crucix:sustained_narrative] energy persistent across 20 sweeps (max strength 10/10, current 10/10)",
        "weight": 1.275,
        "source": "crucix",
        "tier": "A",
        "direction": "bearish",
        "severity": "critical"
      },
      {
        "id": "crucix_sustained_geo_political_1782734482_b31e65",
        "headline": "[crucix:sustained_narrative] geo_political persistent across 20 sweeps (max strength 10/10, current 10/10)",
        "weight": 1.275,
        "source": "crucix",
        "tier": "A",
        "direction": "bearish",
        "severity": "critical"
      },
      {
        "id": "crucix_sustained_macro_1782734482_fd1145",
        "headline": "[crucix:sustained_narrative] macro persistent across 20 sweeps (max strength 10/10, current 10/10)",
        "weight": 1.275,
        "source": "crucix",
        "tier": "A",
        "direction": "ambiguous",
        "severity": "critical"
      },
      {
        "id": "crucix_sustained_political_1782734482_e57b99",
        "headline": "[crucix:sustained_narrative] political persistent across 20 sweeps (max strength 10/10, current 7/10)",
        "weight": 1.275,
        "source": "crucix",
        "tier": "A",
        "direction": "ambiguous",
        "severity": "critical"
      },
      {
        "id": "crucix_sustained_social_1782734482_5544b8",
        "headline": "[crucix:sustained_narrative] social persistent across 20 sweeps (max strength 7/10, current 6/10)",
        "weight": 1.275,
        "source": "crucix",
        "tier": "A",
        "direction": "neutral",
        "severity": "critical"
      }
    ],
    "_synthesized_at": "2026-06-29T08:01:22.214278-04:00",
    "legacy_invariants": [
      {
        "source": "invariants",
        "type": "top_signature",
        "strength": 16.7
      },
      {
        "source": "invariants",
        "type": "bottom_signature",
        "strength": 50.0
      }
    ]
  },
  "regime": "stable",
  "regime_break_signal": false,
  "jordan_read": "panic phase flat, aug 2024 bottom analogue dominant, inverse path active per thesis, bearish leverage on forecast, score 38 low cliff, etf_net_total and mvrv_zscore heaviest bearish factors, j6 line leading; brains advisory but your call settles on Panic; pattern_trigger analogs mixed outcomes weighed, watch meme-buy/dump dynamics and perp_long activity for divergence",
  "jordan_voice": "Done panicking, hasn't started believing. The boring part. Fear keeps the market in holding pattern while the bottom analogue plays out. ETF outflows accelerating, on-chain valuation stretched, rhymes hard with August 2024 bottom. Pattern trigger shows mixed historical outcomes in similar regimes \u2014 one slight gain amid mostly small losses; watch for sudden meme or perp_long shifts as potential divergence.",
  "read_source": "jordan",
  "trade_recommendation": {
    "perps": "neutral",
    "kalshi_btc_weekly_up": "neutral",
    "sniper_aggression": "conservative",
    "exit_priority_signals": [
      "critical crucix signal: [crucix:sustained_narrative] energy persistent across 20 sweeps (max strength 10/10, current 10/10)",
      "critical crucix signal: [crucix:sustained_narrative] geo_political persistent across 20 sweeps (max strength 10/10, current ",
      "critical crucix signal: [crucix:sustained_narrative] macro persistent across 20 sweeps (max strength 10/10, current 10/10)"
    ],
    "abort_conditions": [],
    "reasoning": "Flat trend, regime unclear, wait for direction."
  }
}