{
  "_updated": "2026-06-28T08:14:34.008906-04:00",
  "board": {
    "phase": {
      "analyst": {
        "opinion": "Denial",
        "why": "Score=38 falls in Denial (32-38), and \u00b11 rung rule allows Panic/Anxiety, but Denial is the anchor phase."
      },
      "narrative": {
        "opinion": "Denial",
        "why": "Score 38 sits in Denial (32-38)"
      },
      "judge": {
        "opinion": "Denial",
        "why": "The score of 38 places us in the Denial phase, with a slight lean towards Anxiety due to the nervousness in the market."
      }
    },
    "leverage_bias": {
      "analyst": {
        "opinion": "BEAR",
        "why": "Denial phase is bearish, despite LONG position; trend is descending leg."
      },
      "narrative": {
        "opinion": "NEUTRAL",
        "why": "Current phase suggests uncertainty"
      },
      "judge": {
        "opinion": "BEAR",
        "why": "The current data suggests a downward trend and the historical match points towards a bear cycle."
      }
    },
    "winning_line": {
      "analyst": {
        "opinion": "bottom_2022_may_luna",
        "why": "Best_match=bottom_2022_may_luna (0.8093) aligns with current Denial phase and score."
      },
      "narrative": {
        "opinion": "My line",
        "why": "I'm weighting fear and ETF flows over slow rates"
      },
      "judge": {
        "opinion": "BTC=$60280",
        "why": "This is the current market price, indicating where the market is currently trading."
      }
    },
    "horse_race_read": {
      "analyst": {
        "opinion": "My line's ahead because Denial phase matches 2022 analog's early recovery skepticism, unlike weaker analogs that overestimate bounce strength.",
        "why": "Historical match prioritizes fear-driven selling over premature optimism."
      },
      "narrative": null,
      "judge": {
        "opinion": "The BTC line is winning due to its current pricing being the most reflective of the market's sentiment and trend.",
        "why": "The residual standings show that this line tracks reality best, aligning with the current downward trend."
      }
    },
    "reset_euphoria": {
      "analyst": {
        "opinion": "hold",
        "why": "Not at Euphoria (93-100); Denial is bear leg, not post-peak."
      },
      "narrative": {
        "opinion": "hold",
        "why": "Not enough evidence of a bear cycle turn yet"
      },
      "judge": {
        "opinion": "hold",
        "why": "We have not yet officially turned into a bear cycle; therefore, we should not clear the Euphoria phase flag."
      }
    },
    "pattern_match": {
      "analyst": {
        "opinion": "bottom_2022_may_luna",
        "why": "Best_match=bottom_2022_may_luna (0.8093) confirms historical phase alignment."
      },
      "narrative": {
        "opinion": "bottom_2022_may_luna",
        "why": "Highest similarity score (0.8093)"
      },
      "judge": {
        "opinion": "bottom_2022_may_luna",
        "why": "The historical match with this pattern suggests that we are at a similar stage of market recovery as in May 2022."
      }
    },
    "the_read": {
      "analyst": {
        "opinion": "Denial phase with bearish bias; LONG position risks misalignment with descending leg.",
        "why": "Denial is bear leg, but LONG exposure may require caution."
      },
      "narrative": {
        "opinion": "Current phase is Denial, maintain neutral leverage bias until more conviction builds."
      },
      "judge": {
        "opinion": "We are currently in the Denial phase, witnessing a bearish trend with a slight nervousness in the market. The historical pattern of May 2022 is a good reference for potential future movements.",
        "why": "The combination of the current score, trend, and historical match indicates this synthesized view."
      }
    },
    "voice": {
      "analyst": {
        "opinion": "Market in denial of downtrend; bearish leg continues despite longs.",
        "why": "Denial phase reflects refusal to accept decline, typical of bear cycles."
      },
      "narrative": "Market seems uncertain but not yet capitulating, waiting for clearer signs before committing.",
      "judge": {
        "opinion": "The market seems to be in Denial phase, showing signs of nervousness as we approach a bearish trend. Stay cautious and monitor the market closely for potential reversals.",
        "why": "This narrative reflects the current market sentiment and aligns with the analysis provided."
      }
    },
    "cliff_proximity": {
      "analyst": {
        "opinion": "low",
        "why": "Denial is early bear leg; cliff proximity increases later (e.g., Euphoria)."
      },
      "narrative": {
        "opinion": "Low",
        "why": "Not in the late stages of a cycle"
      },
      "judge": {
        "opinion": "moderate",
        "why": "The score of 38 indicates a moderate proximity to a cliff/break, suggesting caution is needed but not an immediate crisis."
      }
    },
    "cycle_position": {
      "analyst": {
        "opinion": "Bear leg (descent from peak)",
        "why": "Denial is part of bear cycle's downward phase."
      },
      "narrative": {
        "opinion": "Mid-cycle",
        "why": "Not at peak or trough"
      },
      "judge": {
        "opinion": "descending leg",
        "why": "Given the current trend and phase, we are in the descending leg of the broader market cycle."
      }
    },
    "surprise_index": {
      "analyst": {
        "opinion": "50",
        "why": "Score=38 at Denial's upper bound is moderate surprise; no clear anomaly."
      },
      "narrative": {
        "opinion": "50",
        "why": "Current data is roughly as expected"
      },
      "judge": {
        "opinion": "50",
        "why": "The current data is neither too surprising nor too expected, aligning with the typical movements within this phase."
      }
    },
    "invariants_firing": {
      "analyst": {
        "opinion": "Fear-driven selling, low participation",
        "why": "Denial phase invariants include skepticism and forced selling."
      },
      "narrative": [
        "Invariant X"
      ],
      "judge": {
        "opinion": [
          "trend",
          "score",
          "historical_match"
        ],
        "why": "These factors are critical in determining the market's current state and future direction."
      }
    },
    "falsification": {
      "analyst": {
        "opinion": "Strong rally to 70+ score (Hope) would falsify Denial thesis.",
        "why": "A move to Hope would indicate trend reversal."
      },
      "narrative": "A sudden spike in buying volume would falsify the current thesis.",
      "judge": {
        "opinion": "a significant upward trend reversal",
        "why": "If there is a sudden and sustained upward trend, it would falsify the bearish thesis we currently hold."
      }
    },
    "detections": {
      "analyst": {
        "opinion": "Denial phase confirmed by score=38; 2022 analog match strengthens bear case.",
        "why": "Score and historical pattern align with bear leg dynamics."
      },
      "narrative": "Engine flagged increased selling pressure and decreasing open interest.",
      "judge": {
        "opinion": [
          "score",
          "trend",
          "historical_match"
        ],
        "why": "These detections are crucial in understanding the current market dynamics and aligning with the phase analysis."
      }
    },
    "data_gaps": {
      "analyst": {
        "opinion": "Trend unspecified; consensus_phase=None",
        "why": "Missing trend data weakens directional certainty."
      },
      "narrative": {
        "opinion": "ETF flows",
        "why": "Important for understanding institutional sentiment"
      },
      "judge": {
        "opinion": [
          "leverage_bias",
          "winning_line"
        ],
        "why": "These data gaps are important for a comprehensive understanding of market sentiment and trend direction."
      }
    },
    "exit_priority_signal": {
      "analyst": {
        "opinion": "Move to Anxiety (39-46) or confirmation of bear leg",
        "why": "Denial phase exit triggers on trend confirmation or phase shift."
      },
      "narrative": {
        "opinion": "Significant change in ETF flows",
        "why": "Could indicate a shift in market sentiment"
      },
      "judge": {
        "opinion": "trend reversal signal",
        "why": "Monitoring for a trend reversal signal is the priority as it would indicate a potential shift in the bearish trend."
      }
    }
  },
  "_status": {
    "analyst": "ok",
    "narrative": "ok",
    "judge": "ok"
  }
}