{
  "_updated": "2026-07-10T18:46:03.745110-04:00",
  "daily_days": 7,
  "horizon_weeks": 104,
  "_doctrine": "J6 curated price: mechanical BTC-anchored base + Jordan's conviction tilt + per-asset catalyst bias (decaying, stacked, persisted). The line perps trades.",
  "start_date": "2026-07-10",
  "end_date": "2028-07-07",
  "j6_directional_tilt": 2.43,
  "terminal_bias_pct": 2.92,
  "active_catalyst_biases": {},
  "betas": {
    "BTC": 1.0,
    "ETH": 1.16,
    "SOL": 1.38
  },
  "cycle_position": {
    "marker": "HUNTING_TOP",
    "confidence": 0.86,
    "off_extreme_pct": 6.0,
    "days_since_extreme": 16,
    "recent_low": 36.0,
    "recent_high": 63.0,
    "current": 42.0,
    "ma_200w_gate": "200wk MA CONFIRMS bottom (BTC 1.02x floor \u2014 at the cycle floor).",
    "note": "bottom appears IN: rising, score 6pts off the low (36) over 16d. Hunting the top. High confidence. 200wk MA CONFIRMS bottom (BTC 1.02x floor \u2014 at the cycle floor)."
  },
  "rotation": {
    "rotating": false,
    "strength": 0.2,
    "eth_rs": 9.04,
    "sol_rs": 20.12,
    "dom_trend": 0.0,
    "note": "alts outperforming (ETH +9% / SOL +20% vs BTC) but dom not confirming trend (+0.0pt) \u2014 could be a transient pump, not rotation yet."
  },
  "contributing_analogs": [
    {
      "name": "bottom_2024_aug",
      "similarity": 0.752,
      "date": "2024-08-05",
      "weight": 0.34
    },
    {
      "name": "bottom_2022_may_luna",
      "similarity": 0.738,
      "date": "2022-05-12",
      "weight": 0.334
    },
    {
      "name": "bottom_2020_mar",
      "similarity": 0.72,
      "date": "2020-03-12",
      "weight": 0.326
    }
  ],
  "assets": {
    "BTC": {
      "current": 64093,
      "beta": 1.0,
      "daily_pct": [
        0.04,
        0.51,
        -1.66,
        -1.25,
        -2.51,
        4.73,
        4.94
      ],
      "daily_price": [
        64119.7,
        64422.0,
        63032.24,
        63289.68,
        62483.17,
        67124.56,
        67260.22
      ],
      "weekly_pct": [
        -4.04,
        0.62,
        1.07,
        -11.92,
        -9.59,
        1.77,
        6.01,
        3.88,
        9.39,
        12.04,
        14.98,
        18.94,
        24.23,
        27.11,
        28.48,
        26.56,
        26.89,
        26.48,
        28.78,
        31.67,
        33.4,
        33.0,
        37.65,
        37.56,
        24.23,
        27.8,
        24.44,
        28.84,
        27.73,
        25.4,
        32.46,
        34.95,
        36.19,
        43.06,
        61.18,
        71.05,
        80.21,
        75.44,
        95.06,
        104.35,
        131.17,
        165.15,
        170.47,
        165.11,
        138.53,
        176.91,
        215.29,
        254.11,
        240.78,
        248.05,
        271.1,
        288.8,
        257.45,
        286.75,
        269.54,
        304.65,
        268.11,
        272.9,
        284.19,
        250.1,
        184.94,
        190.61,
        184.35,
        180.51,
        180.52,
        149.4,
        152.96,
        147.66,
        143.45,
        139.54,
        176.97,
        176.66,
        206.55,
        205.36,
        235.02,
        232.01,
        213.47,
        221.6,
        197.03,
        186.24,
        258.42,
        267.96,
        315.24,
        276.14,
        297.06,
        313.35,
        287.34,
        265.37,
        274.63,
        244.52,
        246.37,
        242.11,
        243.32,
        230.9,
        233.36,
        220.06,
        197.49,
        192.48,
        236.03,
        224.39,
        289.71,
        328.78,
        319.29,
        321.48
      ],
      "weekly_price": [
        61502.39,
        64487.86,
        64781.43,
        56454.49,
        57946.6,
        65226.31,
        67942.6,
        66582.57,
        70112.84,
        71810.04,
        73693.12,
        76229.95,
        79625.62,
        81470.24,
        82347.06,
        81115.21,
        81325.46,
        81067.83,
        82540.72,
        84391.75,
        85499.3,
        85241.67,
        88227.15,
        88168.2,
        79623.35,
        81910.21,
        79755.43,
        82574.27,
        81867.99,
        80373.36,
        84897.07,
        86491.73,
        87285.22,
        91693.57,
        103305.96,
        109630.68,
        115500.34,
        112441.85,
        125022.05,
        130975.03,
        148163.52,
        169941.06,
        173349.55,
        169919.32,
        152882.14,
        177479.78,
        202077.41,
        226957.06,
        218418.62,
        223076.92,
        237849.1,
        249192.3,
        229097.89,
        247882.29,
        236850.63,
        259352.42,
        235931.58,
        239000.38,
        246241.63,
        224391.07,
        182626.82,
        186259.63,
        182246.15,
        179790.13,
        179795.29,
        159848.29,
        162128.74,
        158730.55,
        156037.39,
        153530.1,
        177518.85,
        177318.9,
        196475.05,
        195717.49,
        214726.22,
        212795.76,
        200911.66,
        206121.17,
        190372.26,
        183461.78,
        229722.85,
        235836.06,
        266137.97,
        241076.35,
        254489.76,
        264929.25,
        248257.41,
        234174.92,
        240108.67,
        220815.42,
        221999.89,
        219268.27,
        220042.53,
        212080.93,
        213662.77,
        205137.14,
        190670.09,
        187457.78,
        215369.02,
        207913.75,
        249778.04,
        274817.92,
        268734.23,
        270136.61
      ],
      "mechanical_pct": [
        -4.07,
        0.56,
        0.99,
        -12.03,
        -9.73,
        1.6,
        5.81,
        3.66,
        9.14,
        11.76,
        14.67,
        18.6,
        23.87,
        26.72,
        28.06,
        26.11,
        26.41,
        25.98,
        28.25,
        31.11,
        32.81,
        32.38,
        37.01,
        36.89,
        23.53,
        27.07,
        23.68,
        28.05,
        26.92,
        24.56,
        31.59,
        34.05,
        35.26,
        42.11,
        60.2,
        70.04,
        79.17,
        74.37,
        93.97,
        103.23,
        130.02,
        163.97,
        169.26,
        163.88,
        137.27,
        175.62,
        213.97,
        252.76,
        239.41,
        246.65,
        269.67,
        287.34,
        255.96,
        285.24,
        268.0,
        303.08,
        266.51,
        271.27,
        282.54,
        248.42,
        183.23,
        188.87,
        182.58,
        178.72,
        178.7,
        147.55,
        151.08,
        145.75,
        141.52,
        137.58,
        174.98,
        174.64,
        204.5,
        203.29,
        232.92,
        229.88,
        211.31,
        219.41,
        194.81,
        184.0,
        256.15,
        265.66,
        312.91,
        273.78,
        294.68,
        310.94,
        284.9,
        262.9,
        272.13,
        242.0,
        243.82,
        239.53,
        240.71,
        228.26,
        230.7,
        217.37,
        194.77,
        189.73,
        233.25,
        221.59,
        286.88,
        325.92,
        316.4,
        318.56
      ],
      "catalyst_bias_pct": 0.0
    },
    "ETH": {
      "current": 1793.77,
      "beta": 1.16,
      "daily_pct": [
        0.04,
        0.58,
        -1.94,
        -1.48,
        -2.95,
        5.45,
        5.68
      ],
      "daily_price": [
        1794.52,
        1804.23,
        1759.06,
        1767.16,
        1740.82,
        1891.53,
        1895.68
      ],
      "weekly_pct": [
        -4.58,
        0.94,
        1.57,
        -13.39,
        -10.58,
        2.7,
        7.73,
        5.37,
        11.76,
        14.83,
        18.23,
        22.82,
        28.95,
        32.28,
        33.88,
        31.64,
        32.02,
        31.54,
        34.2,
        37.55,
        39.55,
        39.09,
        44.47,
        44.37,
        28.9,
        33.04,
        29.14,
        34.23,
        32.94,
        30.23,
        38.42,
        41.31,
        42.74,
        50.7,
        71.71,
        83.16,
        93.78,
        88.25,
        110.99,
        121.78,
        152.87,
        192.29,
        198.46,
        192.23,
        161.4,
        205.92,
        250.43,
        295.45,
        279.99,
        288.42,
        315.15,
        335.68,
        299.31,
        333.3,
        313.32,
        354.05,
        311.66,
        317.2,
        330.3,
        290.75,
        215.16,
        221.73,
        214.47,
        210.01,
        210.02,
        173.91,
        178.04,
        171.89,
        167.0,
        162.45,
        205.88,
        205.51,
        240.17,
        238.79,
        273.19,
        269.69,
        248.18,
        257.61,
        229.11,
        216.58,
        300.31,
        311.37,
        366.21,
        320.85,
        345.11,
        364.0,
        333.83,
        308.34,
        319.07,
        284.15,
        286.28,
        281.33,
        282.74,
        268.33,
        271.17,
        255.74,
        229.56,
        223.74,
        274.25,
        260.75,
        336.52,
        381.83,
        370.82,
        373.35
      ],
      "weekly_price": [
        1711.58,
        1810.56,
        1822.01,
        1553.62,
        1603.99,
        1842.17,
        1932.36,
        1890.17,
        2004.76,
        2059.79,
        2120.75,
        2203.04,
        2313.15,
        2372.84,
        2401.51,
        2361.29,
        2368.08,
        2359.61,
        2407.29,
        2467.34,
        2503.18,
        2494.9,
        2591.55,
        2589.72,
        2312.19,
        2386.41,
        2316.42,
        2407.69,
        2384.69,
        2336.05,
        2482.92,
        2534.73,
        2560.34,
        2703.27,
        3080.11,
        3285.46,
        3475.92,
        3376.69,
        3784.74,
        3978.25,
        4535.9,
        5242.97,
        5353.61,
        5242.0,
        4688.95,
        5487.5,
        6285.87,
        7093.39,
        6816.22,
        6967.4,
        7446.84,
        7815.06,
        7162.63,
        7772.48,
        7414.05,
        8144.62,
        7384.2,
        7483.54,
        7718.67,
        7009.2,
        5653.25,
        5771.07,
        5640.8,
        5560.95,
        5561.09,
        4913.33,
        4987.37,
        4877.02,
        4789.45,
        4707.8,
        5486.8,
        5480.12,
        6101.81,
        6077.2,
        6694.22,
        6631.4,
        6245.53,
        6414.65,
        5903.39,
        5678.77,
        7180.66,
        7379.02,
        8362.68,
        7549.0,
        7984.31,
        8323.12,
        7781.9,
        7324.63,
        7517.07,
        6890.83,
        6929.0,
        6840.17,
        6865.43,
        6606.91,
        6658.0,
        6381.19,
        5911.54,
        5807.11,
        6713.11,
        6471.09,
        7830.2,
        8642.92,
        8445.39,
        8490.74
      ],
      "mechanical_pct": [
        -4.61,
        0.88,
        1.49,
        -13.5,
        -10.72,
        2.53,
        7.53,
        5.15,
        11.51,
        14.55,
        17.92,
        22.48,
        28.59,
        31.89,
        33.46,
        31.19,
        31.54,
        31.04,
        33.67,
        36.99,
        38.96,
        38.47,
        43.83,
        43.7,
        28.2,
        32.31,
        28.38,
        33.44,
        32.13,
        29.39,
        37.55,
        40.41,
        41.81,
        49.75,
        70.73,
        82.15,
        92.74,
        87.18,
        109.9,
        120.66,
        151.72,
        191.11,
        197.25,
        191.0,
        160.14,
        204.63,
        249.11,
        294.1,
        278.62,
        287.02,
        313.72,
        334.22,
        297.82,
        331.79,
        311.78,
        352.48,
        310.06,
        315.57,
        328.65,
        289.07,
        213.45,
        219.99,
        212.7,
        208.22,
        208.2,
        172.06,
        176.16,
        169.98,
        165.07,
        160.49,
        203.89,
        203.49,
        238.12,
        236.72,
        271.09,
        267.56,
        246.02,
        255.42,
        226.89,
        214.34,
        298.04,
        309.07,
        363.88,
        318.49,
        342.73,
        361.59,
        331.39,
        305.87,
        316.57,
        281.63,
        283.73,
        278.75,
        280.13,
        265.69,
        268.51,
        253.05,
        226.84,
        220.99,
        271.47,
        257.95,
        333.69,
        378.97,
        367.93,
        370.43
      ],
      "catalyst_bias_pct": 0.0
    },
    "SOL": {
      "current": 78.0,
      "beta": 1.38,
      "daily_pct": [
        0.04,
        0.67,
        -2.34,
        -1.79,
        -3.54,
        6.43,
        6.71
      ],
      "daily_price": [
        78.03,
        78.53,
        76.18,
        76.6,
        75.24,
        83.02,
        83.24
      ],
      "weekly_pct": [
        -5.34,
        1.34,
        2.2,
        -15.49,
        -12.03,
        3.89,
        9.98,
        7.28,
        14.88,
        18.52,
        22.56,
        28.02,
        35.31,
        39.27,
        41.16,
        38.49,
        38.94,
        38.36,
        41.52,
        45.51,
        47.88,
        47.32,
        53.72,
        53.59,
        35.18,
        40.1,
        35.46,
        41.51,
        39.97,
        36.74,
        46.48,
        49.91,
        51.6,
        61.07,
        86.06,
        99.68,
        112.31,
        105.72,
        132.78,
        145.6,
        182.59,
        229.47,
        236.81,
        229.4,
        192.7,
        245.66,
        298.61,
        352.17,
        333.77,
        343.79,
        375.58,
        400.0,
        356.73,
        397.16,
        373.39,
        421.83,
        371.4,
        377.99,
        393.57,
        346.51,
        256.58,
        264.39,
        255.74,
        250.44,
        250.44,
        207.48,
        212.39,
        205.06,
        199.24,
        193.83,
        245.48,
        245.04,
        286.27,
        284.62,
        325.55,
        321.37,
        295.78,
        306.99,
        273.07,
        258.17,
        357.77,
        370.93,
        436.15,
        382.19,
        411.05,
        433.52,
        397.62,
        367.29,
        380.05,
        338.49,
        341.03,
        335.14,
        336.8,
        319.66,
        323.03,
        304.67,
        273.52,
        266.58,
        326.67,
        310.61,
        400.74,
        454.64,
        441.54,
        444.54
      ],
      "weekly_price": [
        73.83,
        79.04,
        79.72,
        65.92,
        68.62,
        81.03,
        85.78,
        83.68,
        89.61,
        92.45,
        95.6,
        99.85,
        105.55,
        108.63,
        110.11,
        108.02,
        108.37,
        107.92,
        110.39,
        113.5,
        115.35,
        114.91,
        119.91,
        119.8,
        105.44,
        109.28,
        105.66,
        110.37,
        109.18,
        106.66,
        114.25,
        116.93,
        118.24,
        125.64,
        145.13,
        155.75,
        165.6,
        160.46,
        181.57,
        191.57,
        220.42,
        256.98,
        262.71,
        256.93,
        228.31,
        269.61,
        310.91,
        352.69,
        338.34,
        346.16,
        370.95,
        390.0,
        356.25,
        387.79,
        369.25,
        407.03,
        367.69,
        372.83,
        384.99,
        348.28,
        278.13,
        284.22,
        277.47,
        273.35,
        273.35,
        239.83,
        243.66,
        237.94,
        233.41,
        229.19,
        269.47,
        269.13,
        301.29,
        300.01,
        331.93,
        328.67,
        308.71,
        317.45,
        290.99,
        279.38,
        357.06,
        367.32,
        418.19,
        376.1,
        398.62,
        416.15,
        388.14,
        364.48,
        374.44,
        342.02,
        344.0,
        339.41,
        340.7,
        327.33,
        329.97,
        315.64,
        291.35,
        285.93,
        332.8,
        320.28,
        390.58,
        432.62,
        422.4,
        424.74
      ],
      "mechanical_pct": [
        -5.37,
        1.28,
        2.12,
        -15.6,
        -12.17,
        3.72,
        9.78,
        7.06,
        14.63,
        18.24,
        22.25,
        27.68,
        34.95,
        38.88,
        40.74,
        38.04,
        38.46,
        37.86,
        40.99,
        44.95,
        47.29,
        46.7,
        53.08,
        52.92,
        34.48,
        39.37,
        34.7,
        40.72,
        39.16,
        35.9,
        45.61,
        49.01,
        50.67,
        60.12,
        85.08,
        98.67,
        111.27,
        104.65,
        131.69,
        144.48,
        181.44,
        228.29,
        235.6,
        228.17,
        191.44,
        244.37,
        297.29,
        350.82,
        332.4,
        342.39,
        374.15,
        398.54,
        355.24,
        395.65,
        371.85,
        420.26,
        369.8,
        376.36,
        391.92,
        344.83,
        254.87,
        262.65,
        253.97,
        248.65,
        248.62,
        205.63,
        210.51,
        203.15,
        197.31,
        191.87,
        243.49,
        243.02,
        284.22,
        282.55,
        323.45,
        319.24,
        293.62,
        304.8,
        270.85,
        255.93,
        355.5,
        368.63,
        433.82,
        379.83,
        408.67,
        431.11,
        395.18,
        364.82,
        377.55,
        335.97,
        338.48,
        332.56,
        334.19,
        317.02,
        320.37,
        301.98,
        270.8,
        263.83,
        323.89,
        307.81,
        397.91,
        451.78,
        438.65,
        441.62
      ],
      "catalyst_bias_pct": 0.0
    }
  },
  "method": "btc_anchored_beta_scaled"
}