{
  "_updated": "2026-07-01T02:58:29.398156-04:00",
  "daily_days": 7,
  "horizon_weeks": 104,
  "_doctrine": "BTC-anchored: BTC off clean analogs, ETH/SOL = BTC path x healthy-period beta (rising toward Euphoria). Daily for 7d then weekly. Mechanical; J6 adds catalyst overlay.",
  "assets": {
    "BTC": {
      "current": 58580,
      "beta": 1.0,
      "daily_pct": [
        0.0,
        3.98,
        0.41,
        6.02,
        1.98,
        10.96,
        9.63
      ],
      "daily_price": [
        58580.0,
        60911.48,
        58820.18,
        62106.52,
        59739.88,
        65000.37,
        64221.25
      ],
      "weekly_pct": [
        -3.06,
        9.6,
        7.45,
        15.19,
        10.47,
        1.02,
        4.24,
        9.62,
        17.37,
        18.75,
        19.75,
        24.24,
        25.87,
        28.88,
        23.44,
        21.3,
        31.54,
        31.25,
        30.23,
        29.82,
        47.68,
        67.91,
        70.54,
        77.26,
        72.66,
        63.52,
        72.78,
        92.7,
        86.96,
        102.82,
        95.73,
        90.5,
        91.69,
        115.72,
        120.26,
        129.87,
        144.41,
        138.32,
        146.38,
        141.64,
        171.0,
        171.32,
        206.14,
        257.76,
        237.41,
        221.01,
        237.78,
        262.81,
        310.61,
        354.81,
        295.27,
        314.03,
        387.3,
        373.88,
        359.26,
        375.45,
        391.62,
        402.39,
        341.0,
        393.97,
        403.85,
        323.98,
        262.91,
        235.65,
        231.77,
        204.41,
        214.88,
        194.05,
        218.24,
        207.54,
        196.08,
        222.59,
        280.41,
        298.07,
        324.7,
        332.25,
        348.96,
        354.01,
        322.49,
        342.4,
        301.8,
        336.03,
        385.29,
        420.06,
        442.3,
        446.92,
        453.46,
        475.13,
        438.65,
        407.0,
        359.27,
        369.18,
        356.03,
        381.5,
        376.42,
        352.36,
        359.93,
        318.97,
        349.79,
        386.03,
        397.5,
        399.99,
        402.95,
        401.29
      ],
      "weekly_price": [
        56784.94,
        64201.48,
        62945.51,
        67481.23,
        64711.73,
        59175.08,
        61065.14,
        64215.4,
        68753.54,
        69566.0,
        70149.1,
        72780.69,
        73737.35,
        75498.81,
        72309.8,
        71058.89,
        77057.48,
        76885.8,
        76286.48,
        76050.36,
        86513.2,
        98359.88,
        99900.08,
        103840.71,
        101141.52,
        95792.72,
        101212.27,
        112885.91,
        109521.62,
        118812.41,
        114660.89,
        111594.9,
        112291.55,
        126367.42,
        129030.56,
        134657.4,
        143177.63,
        139606.05,
        144330.31,
        141554.06,
        158754.05,
        158937.9,
        179335.01,
        209573.1,
        197655.68,
        188046.31,
        197872.88,
        212533.65,
        240537.14,
        266428.15,
        231549.62,
        242538.32,
        285462.59,
        277600.71,
        269036.31,
        278516.81,
        287991.45,
        294300.96,
        258339.6,
        289366.27,
        295153.98,
        248367.93,
        212593.13,
        196623.77,
        194351.77,
        178324.28,
        184454.9,
        172252.24,
        186424.54,
        180159.64,
        173443.21,
        188970.97,
        222845.53,
        233190.31,
        248791.96,
        253211.15,
        262999.87,
        265959.96,
        247495.99,
        259160.17,
        235371.74,
        255427.73,
        284281.98,
        304651.6,
        317682.04,
        320383.48,
        324217.77,
        336913.86,
        315540.27,
        296998.35,
        269040.82,
        274842.94,
        267141.47,
        282064.95,
        279088.64,
        264995.19,
        269426.99,
        245434.88,
        263485.52,
        284713.71,
        291438.43,
        292896.75,
        294628.84,
        293654.01
      ],
      "band_low_pct": [
        0.0,
        -2.22,
        -4.27,
        -0.89,
        -5.78,
        -36.82,
        -28.57,
        -36.07,
        -28.27,
        -29.6,
        -25.37,
        -21.41,
        -23.72,
        -18.86,
        -29.68,
        -33.42,
        -34.12,
        -27.97,
        -33.13,
        -37.09,
        -35.84,
        -35.5,
        -36.66,
        -36.19,
        -30.84,
        -29.3,
        -44.19,
        -44.48,
        -45.3,
        -43.83,
        -43.1,
        -44.2,
        -44.03,
        -45.03,
        -43.67,
        -30.31,
        -24.33,
        -23.49,
        -22.49,
        -27.34,
        -18.14,
        -23.01,
        -25.74,
        -31.46,
        -10.42,
        -8.66,
        -5.62,
        -7.15,
        0.72,
        -7.59,
        -2.83,
        -3.98,
        -11.02,
        -9.87,
        -10.74,
        -10.05,
        -14.12,
        -11.93,
        1.49,
        1.62,
        0.64,
        0.65,
        -1.09,
        -2.47,
        -3.52,
        -2.28,
        -13.31,
        -13.6,
        -14.06,
        -13.97,
        -11.74,
        -11.7,
        -10.41,
        -7.08,
        -10.76,
        -0.61,
        13.25,
        16.55,
        23.38,
        21.54,
        25.57,
        31.15,
        45.26,
        40.33,
        45.31,
        40.05,
        46.14,
        42.33,
        38.42,
        39.93,
        42.83,
        58.7,
        71.63,
        71.33,
        106.07,
        127.56,
        116.98,
        112.82,
        131.37,
        128.88,
        112.02,
        115.92,
        110.69,
        112.26
      ],
      "band_high_pct": [
        0.0,
        18.94,
        20.03,
        32.06,
        31.9,
        39.56,
        45.57,
        72.85,
        84.49,
        80.31,
        77.09,
        86.53,
        85.63,
        82.2,
        79.46,
        73.94,
        75.61,
        77.69,
        76.12,
        86.09,
        126.13,
        126.02,
        128.17,
        148.34,
        131.51,
        125.62,
        162.85,
        210.53,
        198.46,
        246.49,
        207.26,
        191.69,
        168.46,
        232.94,
        221.01,
        208.98,
        258.48,
        240.7,
        268.32,
        261.58,
        359.0,
        408.37,
        517.79,
        674.07,
        595.68,
        516.64,
        558.98,
        655.06,
        805.81,
        978.76,
        788.18,
        840.56,
        1077.67,
        1021.34,
        976.34,
        1007.69,
        1049.79,
        1066.91,
        862.45,
        1012.0,
        1030.76,
        799.17,
        621.81,
        565.65,
        583.64,
        583.65,
        584.87,
        518.92,
        566.66,
        544.58,
        506.36,
        559.42,
        700.45,
        756.78,
        805.65,
        840.42,
        840.36,
        860.41,
        769.2,
        828.36,
        721.42,
        817.46,
        957.01,
        1070.92,
        1080.56,
        1090.09,
        1083.14,
        1139.71,
        1047.94,
        954.06,
        846.1,
        849.21,
        800.87,
        869.74,
        816.99,
        702.52,
        730.28,
        573.61,
        633.37,
        696.89,
        712.34,
        671.53,
        651.97,
        657.65
      ],
      "news_net": 0,
      "da_daily_price": [
        58580.0,
        56248.52,
        58339.82,
        55053.48,
        57420.12,
        52159.63,
        52938.75
      ],
      "da_weekly_price": [
        60372.55,
        52956.32,
        54215.79,
        49681.7,
        52446.67,
        57982.48,
        56096.21,
        52944.6,
        48404.65,
        47596.25,
        47010.45,
        44380.21,
        43425.35,
        41662.1,
        44848.85,
        46102.46,
        40103.87,
        40273.75,
        40871.27,
        41111.44,
        30649.06,
        18798.32,
        17257.67,
        13321.09,
        16015.77,
        21369.98,
        15945.48,
        4686.4,
        7638.83,
        4686.4,
        4686.4,
        5565.1,
        4868.0,
        4686.4,
        4686.4,
        4686.4,
        4686.4,
        4686.4,
        4686.4,
        4686.4,
        4686.4,
        4686.4,
        4686.4,
        4686.4,
        4686.4,
        4686.4,
        4686.4,
        4686.4,
        4686.4,
        4686.4,
        4686.4,
        4686.4,
        4686.4,
        4686.4,
        4686.4,
        4686.4,
        4686.4,
        4686.4,
        4686.4,
        4686.4,
        4686.4,
        4686.4,
        4686.4,
        4686.4,
        4686.4,
        4686.4,
        4686.4,
        4686.4,
        4686.4,
        4686.4,
        4686.4,
        4686.4,
        4686.4,
        4686.4,
        4686.4,
        4686.4,
        4686.4,
        4686.4,
        4686.4,
        4686.4,
        4686.4,
        4686.4,
        4686.4,
        4686.4,
        4686.4,
        4686.4,
        4686.4,
        4686.4,
        4686.4,
        4686.4,
        4686.4,
        4686.4,
        4686.4,
        4686.4,
        4686.4,
        4686.4,
        4686.4,
        4686.4,
        4686.4,
        4686.4,
        4686.4,
        4686.4,
        4686.4,
        4686.4
      ]
    },
    "ETH": {
      "current": 1572.65,
      "beta": 1.11,
      "daily_pct": [
        0.0,
        4.42,
        0.46,
        6.68,
        2.2,
        12.17,
        10.69
      ],
      "daily_price": [
        1572.65,
        1642.13,
        1579.81,
        1677.74,
        1607.21,
        1763.97,
        1740.76
      ],
      "weekly_pct": [
        -3.4,
        10.65,
        8.27,
        16.87,
        11.62,
        1.13,
        4.71,
        10.68,
        19.28,
        20.82,
        21.92,
        26.91,
        28.72,
        32.06,
        26.02,
        23.65,
        35.01,
        34.69,
        33.55,
        33.1,
        52.93,
        75.38,
        78.3,
        85.76,
        80.65,
        70.51,
        80.78,
        102.9,
        96.53,
        114.13,
        106.26,
        100.46,
        101.78,
        128.45,
        133.49,
        144.15,
        160.3,
        153.53,
        162.48,
        157.22,
        189.81,
        190.16,
        228.81,
        286.11,
        263.53,
        245.32,
        263.94,
        291.72,
        344.78,
        393.84,
        327.75,
        348.57,
        429.91,
        415.01,
        398.78,
        416.75,
        434.7,
        446.65,
        378.51,
        437.3,
        448.27,
        359.62,
        291.83,
        261.57,
        257.27,
        226.9,
        238.51,
        215.39,
        242.25,
        230.37,
        217.65,
        247.07,
        311.26,
        330.86,
        360.42,
        368.8,
        387.34,
        392.95,
        357.97,
        380.07,
        334.99,
        373.0,
        427.67,
        466.27,
        490.96,
        496.08,
        503.34,
        527.4,
        486.9,
        451.77,
        398.79,
        409.78,
        395.19,
        423.47,
        417.83,
        391.12,
        399.52,
        354.06,
        388.26,
        428.49,
        441.23,
        443.99,
        447.28,
        445.43
      ],
      "weekly_price": [
        1519.16,
        1740.17,
        1702.74,
        1837.9,
        1755.37,
        1590.38,
        1646.71,
        1740.58,
        1875.81,
        1900.02,
        1917.4,
        1995.82,
        2024.33,
        2076.82,
        1981.79,
        1944.51,
        2123.27,
        2118.15,
        2100.29,
        2093.25,
        2405.04,
        2758.06,
        2803.96,
        2921.39,
        2840.95,
        2681.56,
        2843.06,
        3190.93,
        3090.67,
        3367.53,
        3243.82,
        3152.46,
        3173.22,
        3592.67,
        3672.03,
        3839.7,
        4093.6,
        3987.17,
        4127.95,
        4045.22,
        4557.76,
        4563.24,
        5171.06,
        6072.13,
        5717.0,
        5430.65,
        5723.48,
        6160.36,
        6994.84,
        7766.37,
        6727.02,
        7054.47,
        8333.59,
        8099.31,
        7844.1,
        8126.61,
        8408.94,
        8596.96,
        7525.34,
        8449.91,
        8622.38,
        7228.19,
        6162.13,
        5686.25,
        5618.55,
        5140.94,
        5323.63,
        4960.0,
        5382.32,
        5195.63,
        4995.49,
        5458.21,
        6467.64,
        6775.91,
        7240.83,
        7372.52,
        7664.21,
        7752.42,
        7202.21,
        7549.79,
        6840.92,
        7438.57,
        8298.41,
        8905.41,
        9293.7,
        9374.2,
        9488.46,
        9866.8,
        9229.88,
        8677.34,
        7844.23,
        8017.13,
        7787.63,
        8232.34,
        8143.65,
        7723.67,
        7855.74,
        7140.79,
        7678.69,
        8311.27,
        8511.66,
        8555.12,
        8606.73,
        8577.68
      ],
      "band_low_pct": [
        0.0,
        -2.46,
        -4.74,
        -0.99,
        -6.42,
        -40.87,
        -31.71,
        -40.04,
        -31.38,
        -32.86,
        -28.16,
        -23.77,
        -26.33,
        -20.93,
        -32.94,
        -37.1,
        -37.87,
        -31.05,
        -36.77,
        -41.17,
        -39.78,
        -39.41,
        -40.69,
        -40.17,
        -34.23,
        -32.52,
        -49.05,
        -49.37,
        -50.28,
        -48.65,
        -47.84,
        -49.06,
        -48.87,
        -49.98,
        -48.47,
        -33.64,
        -27.01,
        -26.07,
        -24.96,
        -30.35,
        -20.14,
        -25.54,
        -28.57,
        -34.92,
        -11.57,
        -9.61,
        -6.24,
        -7.94,
        0.8,
        -8.42,
        -3.14,
        -4.42,
        -12.23,
        -10.96,
        -11.92,
        -11.16,
        -15.67,
        -13.24,
        1.65,
        1.8,
        0.71,
        0.72,
        -1.21,
        -2.74,
        -3.91,
        -2.53,
        -14.77,
        -15.1,
        -15.61,
        -15.51,
        -13.03,
        -12.99,
        -11.56,
        -7.86,
        -11.94,
        -0.68,
        14.71,
        18.37,
        25.95,
        23.91,
        28.38,
        34.58,
        50.24,
        44.77,
        50.29,
        44.46,
        51.22,
        46.99,
        42.65,
        44.32,
        47.54,
        65.16,
        79.51,
        79.18,
        117.74,
        141.59,
        129.85,
        125.23,
        145.82,
        143.06,
        124.34,
        128.67,
        122.87,
        124.61
      ],
      "band_high_pct": [
        0.0,
        21.02,
        22.23,
        35.59,
        35.41,
        43.91,
        50.58,
        80.86,
        93.78,
        89.14,
        85.57,
        96.05,
        95.05,
        91.24,
        88.2,
        82.07,
        83.93,
        86.24,
        84.49,
        95.56,
        140.0,
        139.88,
        142.27,
        164.66,
        145.98,
        139.44,
        180.76,
        233.69,
        220.29,
        273.6,
        230.06,
        212.78,
        186.99,
        258.56,
        245.32,
        231.97,
        286.91,
        267.18,
        297.84,
        290.35,
        398.49,
        453.29,
        574.75,
        748.22,
        661.2,
        573.47,
        620.47,
        727.12,
        894.45,
        1086.42,
        874.88,
        933.02,
        1196.21,
        1133.69,
        1083.74,
        1118.54,
        1165.27,
        1184.27,
        957.32,
        1123.32,
        1144.14,
        887.08,
        690.21,
        627.87,
        647.84,
        647.85,
        649.21,
        576.0,
        628.99,
        604.48,
        562.06,
        620.96,
        777.5,
        840.03,
        894.27,
        932.87,
        932.8,
        955.06,
        853.81,
        919.48,
        800.78,
        907.38,
        1062.28,
        1188.72,
        1199.42,
        1210.0,
        1202.29,
        1265.08,
        1163.21,
        1059.01,
        939.17,
        942.62,
        888.97,
        965.41,
        906.86,
        779.8,
        810.61,
        636.71,
        703.04,
        773.55,
        790.7,
        745.4,
        723.69,
        729.99
      ],
      "news_net": 0,
      "da_daily_price": [
        1572.65,
        1503.14,
        1565.42,
        1467.6,
        1538.05,
        1381.26,
        1404.53
      ],
      "da_weekly_price": [
        1626.12,
        1405.16,
        1442.59,
        1307.34,
        1389.91,
        1554.88,
        1498.58,
        1404.69,
        1269.44,
        1245.22,
        1227.93,
        1149.45,
        1120.98,
        1068.46,
        1163.45,
        1200.72,
        1022.07,
        1027.1,
        1045.03,
        1052.1,
        740.25,
        387.19,
        341.27,
        223.95,
        304.31,
        463.77,
        302.26,
        125.81,
        125.81,
        125.81,
        125.81,
        125.81,
        125.81,
        125.81,
        125.81,
        125.81,
        125.81,
        125.81,
        125.81,
        125.81,
        125.81,
        125.81,
        125.81,
        125.81,
        125.81,
        125.81,
        125.81,
        125.81,
        125.81,
        125.81,
        125.81,
        125.81,
        125.81,
        125.81,
        125.81,
        125.81,
        125.81,
        125.81,
        125.81,
        125.81,
        125.81,
        125.81,
        125.81,
        125.81,
        125.81,
        125.81,
        125.81,
        125.81,
        125.81,
        125.81,
        125.81,
        125.81,
        125.81,
        125.81,
        125.81,
        125.81,
        125.81,
        125.81,
        125.81,
        125.81,
        125.81,
        125.81,
        125.81,
        125.81,
        125.81,
        125.81,
        125.81,
        125.81,
        125.81,
        125.81,
        125.81,
        125.81,
        125.81,
        125.81,
        125.81,
        125.81,
        125.81,
        125.81,
        125.81,
        125.81,
        125.81,
        125.81,
        125.81,
        125.81
      ]
    },
    "SOL": {
      "current": 74.02,
      "beta": 1.31,
      "daily_pct": [
        0.0,
        5.21,
        0.54,
        7.89,
        2.59,
        14.36,
        12.62
      ],
      "daily_price": [
        74.02,
        77.88,
        74.42,
        79.86,
        75.94,
        84.65,
        83.36
      ],
      "weekly_pct": [
        -3.97,
        12.66,
        9.89,
        20.08,
        13.93,
        1.59,
        5.86,
        12.95,
        23.1,
        24.91,
        26.22,
        32.1,
        34.24,
        38.18,
        31.05,
        28.25,
        41.67,
        41.28,
        39.94,
        39.41,
        62.81,
        89.3,
        92.75,
        101.56,
        95.52,
        83.56,
        95.68,
        121.79,
        114.26,
        135.04,
        125.76,
        118.9,
        120.46,
        151.94,
        157.89,
        170.47,
        189.53,
        181.54,
        192.1,
        185.9,
        224.36,
        224.77,
        270.38,
        338.0,
        311.35,
        289.87,
        311.84,
        344.63,
        407.25,
        465.15,
        387.15,
        411.72,
        507.71,
        490.13,
        470.98,
        492.18,
        513.37,
        527.48,
        447.06,
        516.44,
        529.39,
        424.76,
        344.76,
        309.05,
        303.97,
        268.12,
        281.83,
        254.55,
        286.24,
        272.23,
        257.21,
        291.93,
        367.69,
        390.82,
        425.71,
        435.59,
        457.48,
        464.1,
        422.81,
        448.89,
        395.7,
        440.55,
        505.07,
        550.62,
        579.76,
        585.81,
        594.38,
        622.77,
        574.97,
        533.51,
        470.99,
        483.96,
        466.74,
        500.12,
        493.46,
        461.94,
        471.85,
        418.2,
        458.57,
        506.04,
        521.08,
        524.34,
        528.21,
        526.03
      ],
      "weekly_price": [
        71.08,
        83.39,
        81.34,
        88.88,
        84.33,
        75.2,
        78.36,
        83.6,
        91.12,
        92.46,
        93.43,
        97.78,
        99.37,
        102.28,
        97.0,
        94.93,
        104.86,
        104.58,
        103.58,
        103.19,
        120.51,
        140.12,
        142.67,
        149.19,
        144.73,
        135.87,
        144.84,
        164.17,
        158.6,
        173.98,
        167.1,
        162.03,
        163.18,
        186.48,
        190.89,
        200.2,
        214.31,
        208.4,
        216.22,
        211.62,
        240.09,
        240.4,
        274.16,
        324.21,
        304.48,
        288.58,
        304.84,
        329.11,
        375.47,
        418.32,
        360.59,
        378.78,
        449.83,
        436.82,
        422.64,
        438.33,
        454.02,
        464.46,
        404.93,
        456.29,
        465.87,
        388.43,
        329.21,
        302.78,
        299.02,
        272.49,
        282.63,
        262.43,
        285.89,
        275.52,
        264.41,
        290.11,
        346.18,
        363.3,
        389.13,
        396.44,
        412.65,
        417.55,
        386.98,
        406.29,
        366.91,
        400.11,
        447.87,
        481.59,
        503.16,
        507.63,
        513.98,
        535.0,
        499.62,
        468.92,
        422.65,
        432.25,
        419.5,
        444.21,
        439.28,
        415.95,
        423.29,
        383.57,
        413.45,
        448.59,
        459.72,
        462.13,
        465.0,
        463.39
      ],
      "band_low_pct": [
        0.0,
        -2.91,
        -5.59,
        -1.17,
        -7.57,
        -48.23,
        -37.43,
        -47.25,
        -37.03,
        -38.78,
        -33.23,
        -28.05,
        -31.07,
        -24.71,
        -38.88,
        -43.78,
        -44.7,
        -36.64,
        -43.4,
        -48.59,
        -46.95,
        -46.51,
        -48.02,
        -47.41,
        -40.4,
        -38.38,
        -57.89,
        -58.27,
        -59.34,
        -57.42,
        -56.46,
        -57.9,
        -57.68,
        -58.99,
        -57.21,
        -39.71,
        -31.87,
        -30.77,
        -29.46,
        -35.82,
        -23.76,
        -30.14,
        -33.72,
        -41.21,
        -13.65,
        -11.34,
        -7.36,
        -9.37,
        0.94,
        -9.94,
        -3.71,
        -5.21,
        -14.44,
        -12.93,
        -14.07,
        -13.17,
        -18.5,
        -15.63,
        1.95,
        2.12,
        0.84,
        0.85,
        -1.43,
        -3.24,
        -4.61,
        -2.99,
        -17.44,
        -17.82,
        -18.42,
        -18.3,
        -15.38,
        -15.33,
        -13.64,
        -9.27,
        -14.1,
        -0.8,
        17.36,
        21.68,
        30.63,
        28.22,
        33.5,
        40.81,
        59.29,
        52.83,
        59.36,
        52.47,
        60.44,
        55.45,
        50.33,
        52.31,
        56.11,
        76.9,
        93.84,
        93.44,
        138.95,
        167.1,
        153.24,
        147.79,
        172.09,
        168.83,
        146.75,
        151.86,
        145.0,
        147.06
      ],
      "band_high_pct": [
        0.0,
        24.81,
        26.24,
        42.0,
        41.79,
        51.82,
        59.7,
        95.43,
        110.68,
        105.21,
        100.99,
        113.35,
        112.18,
        107.68,
        104.09,
        96.86,
        99.05,
        101.77,
        99.72,
        112.78,
        165.23,
        165.09,
        167.9,
        194.33,
        172.28,
        164.56,
        213.33,
        275.79,
        259.98,
        322.9,
        271.51,
        251.11,
        220.68,
        305.15,
        289.52,
        273.76,
        338.61,
        315.32,
        351.5,
        342.67,
        470.29,
        534.96,
        678.3,
        883.03,
        780.34,
        676.8,
        732.26,
        858.13,
        1055.61,
        1282.18,
        1032.52,
        1101.13,
        1411.75,
        1337.96,
        1279.01,
        1320.07,
        1375.22,
        1397.65,
        1129.81,
        1325.72,
        1350.3,
        1046.91,
        814.57,
        741.0,
        764.57,
        764.58,
        766.18,
        679.79,
        742.32,
        713.4,
        663.33,
        732.84,
        917.59,
        991.38,
        1055.4,
        1100.95,
        1100.87,
        1127.14,
        1007.65,
        1085.15,
        945.06,
        1070.87,
        1253.68,
        1402.91,
        1415.53,
        1428.02,
        1418.91,
        1493.02,
        1372.8,
        1249.82,
        1108.39,
        1112.47,
        1049.14,
        1139.36,
        1070.26,
        920.3,
        956.67,
        751.43,
        829.71,
        912.93,
        933.17,
        879.7,
        854.08,
        861.52
      ],
      "news_net": 0,
      "da_daily_price": [
        74.02,
        70.16,
        73.62,
        68.18,
        72.1,
        63.39,
        64.68
      ],
      "da_weekly_price": [
        76.96,
        64.65,
        66.7,
        59.16,
        63.71,
        72.84,
        69.68,
        64.43,
        56.92,
        55.58,
        54.61,
        50.26,
        48.68,
        45.76,
        51.04,
        53.11,
        43.18,
        43.46,
        44.46,
        44.85,
        27.53,
        7.92,
        5.92,
        5.92,
        5.92,
        12.17,
        5.92,
        5.92,
        5.92,
        5.92,
        5.92,
        5.92,
        5.92,
        5.92,
        5.92,
        5.92,
        5.92,
        5.92,
        5.92,
        5.92,
        5.92,
        5.92,
        5.92,
        5.92,
        5.92,
        5.92,
        5.92,
        5.92,
        5.92,
        5.92,
        5.92,
        5.92,
        5.92,
        5.92,
        5.92,
        5.92,
        5.92,
        5.92,
        5.92,
        5.92,
        5.92,
        5.92,
        5.92,
        5.92,
        5.92,
        5.92,
        5.92,
        5.92,
        5.92,
        5.92,
        5.92,
        5.92,
        5.92,
        5.92,
        5.92,
        5.92,
        5.92,
        5.92,
        5.92,
        5.92,
        5.92,
        5.92,
        5.92,
        5.92,
        5.92,
        5.92,
        5.92,
        5.92,
        5.92,
        5.92,
        5.92,
        5.92,
        5.92,
        5.92,
        5.92,
        5.92,
        5.92,
        5.92,
        5.92,
        5.92,
        5.92,
        5.92,
        5.92,
        5.92
      ]
    }
  },
  "contributing_analogs": [
    {
      "name": "bottom_2022_may_luna",
      "similarity": 0.805,
      "date": "2022-05-12",
      "weight": 0.335
    },
    {
      "name": "bottom_2020_mar",
      "similarity": 0.8,
      "date": "2020-03-12",
      "weight": 0.333
    },
    {
      "name": "bottom_2018_dec",
      "similarity": 0.795,
      "date": "2018-12-15",
      "weight": 0.331
    }
  ],
  "betas": {
    "BTC": 1.0,
    "ETH": 1.11,
    "SOL": 1.31
  },
  "cycle_position": {
    "marker": "HUNTING_TOP",
    "confidence": 0.4,
    "off_extreme_pct": 1.0,
    "days_since_extreme": 7,
    "recent_low": 36.0,
    "recent_high": 63.0,
    "current": 37.0,
    "note": "flat near the low (36) \u2014 coiling. Lean hunting top, low confidence."
  },
  "analog_anchor_shift_days": 2,
  "score_modulation_applied": true,
  "cycle_beta_multiplier": 0.996,
  "rotation": {
    "rotating": false,
    "strength": 0.06,
    "eth_rs": -0.45,
    "sol_rs": 11.5,
    "dom_trend": 0.0,
    "note": "alts outperforming (ETH -0% / SOL +12% vs BTC) but dom not confirming trend (+0.0pt) \u2014 could be a transient pump, not rotation yet."
  },
  "method": "btc_anchored_beta_scaled",
  "start_date": "2026-07-01",
  "end_date": "2028-06-28"
}